README.txt
setup.py
porterdb/__init__.py
porterdb/main.py
porterdb.egg-info/PKG-INFO
porterdb.egg-info/SOURCES.txt
porterdb.egg-info/dependency_links.txt
porterdb.egg-info/top_level.txt