Metadata-Version: 1.0
Name: porterdb
Version: 0.0.1
Summary: a simple document based database manager
Home-page: https://github.com/wrecodde/porterdb
Author: Deji Joseph
Author-email: wrecodde@gmail.com
License: MIT
Platform: UNKNOWN
